pibooth_s3_upload.py
pibooth_s3_upload-1.0.0.dist-info/METADATA
pibooth_s3_upload-1.0.0.dist-info/WHEEL
pibooth_s3_upload-1.0.0.dist-info/entry_points.txt
pibooth_s3_upload-1.0.0.dist-info/top_level.txt
pibooth_s3_upload-1.0.0.dist-info/RECORD
